crispy/__init__.py
crispy/image_ridge_find.py
crispy/scms.py
astro_crispy-0.1.0.dist-info/LICENSE
astro_crispy-0.1.0.dist-info/METADATA
astro_crispy-0.1.0.dist-info/WHEEL
astro_crispy-0.1.0.dist-info/top_level.txt
astro_crispy-0.1.0.dist-info/RECORD
