Metadata-Version: 2.1
Name: astro-crispy
Version: 0.1.0
Summary: Computational Ridge Identification with SCMS for Python
Home-page: https://github.com/mcyc/crispy
Author: Michael Chun-Yuan Chen
Author-email: mcychen@uvic.ca
License: UNKNOWN
Platform: UNKNOWN
Classifier: Programming Language :: Python :: 2
Classifier: License :: OSI Approved :: GNU Lesser General Public License v3 (LGPLv3)
Classifier: Operating System :: OS Independent
Requires-Python: >=2.7
